[
  {
    "mint": "HPbpHkJwSEdY2LC7QkeYhwdvgPfdXT64qpg3pjAUpump",
    "migration_timestamp_utc": "2025-05-29T02:19:57.442955+00:00",
    "source_event_identifier": "txType: migrate",
    "bonding_curve_key": null,
    "market_cap_sol_at_migration": null,
    "tx_type_if_present": "migrate"
  },
  {
    "mint": "4uSCGuu29RK1E1qwntk8JbpeZHwjKG17mrM3XFnUpump",
    "migration_timestamp_utc": "2025-05-29T02:34:52.931853+00:00",
    "source_event_identifier": "txType: migrate",
    "bonding_curve_key": null,
    "market_cap_sol_at_migration": null,
    "tx_type_if_present": "migrate"
  },
  {
    "mint": "4v84RbA625z4J4vko2UzpXXeQVS8ojhemuwU1AsT2QNh",
    "migration_timestamp_utc": "2025-05-29T02:35:25.400356+00:00",
    "source_event_identifier": "txType: migrate",
    "bonding_curve_key": null,
    "market_cap_sol_at_migration": null,
    "tx_type_if_present": "migrate"
  },
  {
    "mint": "5KvzprpkjcMXWWmoS8CiPTWiNuHUzPrM1uSceWKhgp7g",
    "migration_timestamp_utc": "2025-05-29T02:36:03.345218+00:00",
    "source_event_identifier": "txType: migrate",
    "bonding_curve_key": null,
    "market_cap_sol_at_migration": null,
    "tx_type_if_present": "migrate"
  },
  {
    "mint": "3YbAg2VtmkGCSETdBvYpcQVpKs3eT5kTdHQDMpVetBKx",
    "migration_timestamp_utc": "2025-05-29T02:38:46.897983+00:00",
    "source_event_identifier": "txType: migrate",
    "bonding_curve_key": null,
    "market_cap_sol_at_migration": null,
    "tx_type_if_present": "migrate"
  },
  {
    "mint": "GR5o7e8Lft1ffrKZwstpstgM1f3XwD2F6wfLa8Ncpump",
    "migration_timestamp_utc": "2025-05-29T02:39:54.804068+00:00",
    "source_event_identifier": "txType: migrate",
    "bonding_curve_key": null,
    "market_cap_sol_at_migration": null,
    "tx_type_if_present": "migrate"
  },
  {
    "mint": "53sNfSUBH5WDK8zcFmXaBmR1D3ftwpw6k5u5zq5Gpump",
    "migration_timestamp_utc": "2025-05-29T02:45:34.111650+00:00",
    "source_event_identifier": "txType: migrate",
    "bonding_curve_key": null,
    "market_cap_sol_at_migration": null,
    "tx_type_if_present": "migrate"
  },
  {
    "mint": "5two8pMyHcn1aWL5HHYsxFBBrYJf83roREsPD79Spump",
    "migration_timestamp_utc": "2025-05-29T02:59:25.065245+00:00",
    "source_event_identifier": "txType: migrate",
    "bonding_curve_key": null,
    "market_cap_sol_at_migration": null,
    "tx_type_if_present": "migrate"
  },
  {
    "mint": "5kzwv86Fk5aPUaYKw2ZxmEqc6VJkGCbvJpyDz5WBpump",
    "migration_timestamp_utc": "2025-05-29T02:59:32.960999+00:00",
    "source_event_identifier": "txType: migrate",
    "bonding_curve_key": null,
    "market_cap_sol_at_migration": null,
    "tx_type_if_present": "migrate"
  }
]