[
  {
    "mint": "7UsqdrPT7eFRf2uqEuFrv1bZREzsLN7FCVyQxmowpump",
    "migration_timestamp_utc": "2025-05-25T21:13:02.902152+00:00",
    "source_event_identifier": "txType: migrate",
    "bonding_curve_key": null,
    "market_cap_sol_at_migration": null,
    "tx_type_if_present": "migrate"
  },
  {
    "mint": "BB6Aq35bopqCU7QFp1UkPKhj71VNv3o5aaJdMwVmpump",
    "migration_timestamp_utc": "2025-05-25T21:21:12.887559+00:00",
    "source_event_identifier": "txType: migrate",
    "bonding_curve_key": null,
    "market_cap_sol_at_migration": null,
    "tx_type_if_present": "migrate"
  },
  {
    "mint": "EguvRFUPNtmk5Ke9RndmRxuJrHd1DtXu54LoaVt8pump",
    "migration_timestamp_utc": "2025-05-25T21:25:07.525622+00:00",
    "source_event_identifier": "txType: migrate",
    "bonding_curve_key": null,
    "market_cap_sol_at_migration": null,
    "tx_type_if_present": "migrate"
  },
  {
    "mint": "Aj5FVsw4exzorG3of1XpDY1xNXHYWSa9AsMiFKYcpump",
    "migration_timestamp_utc": "2025-05-25T21:27:20.424705+00:00",
    "source_event_identifier": "txType: migrate",
    "bonding_curve_key": null,
    "market_cap_sol_at_migration": null,
    "tx_type_if_present": "migrate"
  },
  {
    "mint": "BVeepZ7qZEkyBwe9ZkfeAuDFU16k6Yro1DVoivR8pump",
    "migration_timestamp_utc": "2025-05-25T21:32:56.502939+00:00",
    "source_event_identifier": "txType: migrate",
    "bonding_curve_key": null,
    "market_cap_sol_at_migration": null,
    "tx_type_if_present": "migrate"
  },
  {
    "mint": "BqqppdYVRE9xjR8dJVWhhGxGp31s9dWGnCGQYcHkpump",
    "migration_timestamp_utc": "2025-05-25T21:39:15.036975+00:00",
    "source_event_identifier": "txType: migrate",
    "bonding_curve_key": null,
    "market_cap_sol_at_migration": null,
    "tx_type_if_present": "migrate"
  },
  {
    "mint": "F3haNr6yQJYwFb9Fe9t7rhKrjawSNBG6H7K5DuTPpump",
    "migration_timestamp_utc": "2025-05-25T21:45:18.067613+00:00",
    "source_event_identifier": "txType: migrate",
    "bonding_curve_key": null,
    "market_cap_sol_at_migration": null,
    "tx_type_if_present": "migrate"
  },
  {
    "mint": "22mC63bD253q5uTVA3zMmGkboFnSKnMNSpG5mTDWQqoc",
    "migration_timestamp_utc": "2025-05-25T21:47:28.210569+00:00",
    "source_event_identifier": "txType: migrate",
    "bonding_curve_key": null,
    "market_cap_sol_at_migration": null,
    "tx_type_if_present": "migrate"
  },
  {
    "mint": "AKSmgXbFqTMcmjKGLLsRHArB7c77hXPi4SNuptpMpump",
    "migration_timestamp_utc": "2025-05-25T21:52:28.199732+00:00",
    "source_event_identifier": "txType: migrate",
    "bonding_curve_key": null,
    "market_cap_sol_at_migration": null,
    "tx_type_if_present": "migrate"
  },
  {
    "mint": "4Ww2maefxnVPjw2RXQCrx6egm52wa2ycs4ud37e83Cw3",
    "migration_timestamp_utc": "2025-05-25T21:52:46.042746+00:00",
    "source_event_identifier": "txType: migrate",
    "bonding_curve_key": null,
    "market_cap_sol_at_migration": null,
    "tx_type_if_present": "migrate"
  },
  {
    "mint": "D3BcLiPUeuTREhcwcWii9C41YcyJzw41VzJmaPkZpump",
    "migration_timestamp_utc": "2025-05-25T21:53:29.052541+00:00",
    "source_event_identifier": "txType: migrate",
    "bonding_curve_key": null,
    "market_cap_sol_at_migration": null,
    "tx_type_if_present": "migrate"
  },
  {
    "mint": "DNfmJPdWQipZpcvBnGzp1GtRUPdC8QyJBdhWnAp8rkAN",
    "migration_timestamp_utc": "2025-05-25T21:59:08.153952+00:00",
    "source_event_identifier": "txType: migrate",
    "bonding_curve_key": null,
    "market_cap_sol_at_migration": null,
    "tx_type_if_present": "migrate"
  }
]